[
  {
    "id": "main",
    "components": [
      "section"
    ]
  },
  {
    "id": "columns",
    "components": []
  },
  {
    "id": "column",
    "components": [
      "text",
      "image",
      "button",
      "title"
    ]
  },
  {
    "id": "section",
    "components": [
      "breadcrumb",
      "text",
      "image",
      "button",
      "title",
      "hero",
      "cards",
      "columns",
      "header-nav",
      "carousel",
      "savingscard",
      "accordion-group",
      "imagedesc-card-inline",
      "car-card",
      "wishlist"
    ]
  },
  {
    "id": "cards",
    "components": [
      "card"
    ]
  },
  {
    "id": "carousel",
    "components": ["silde"]
  },
  {
    "id": "accordion",
    "components": ["accordion"]
  }
]
